create_jupyter_git/__init__.py
create_jupyter_git/__main__.py
create_jupyter_git/is_cwd_git_repo.py
create_jupyter_git/setup_notebook_version_control.py
create_jupyter_git/repo_template/.gitignore
create_jupyter_git/repo_template/notebooks/jupyter_notebook_config.py
create_jupyter_git/repo_template/scripts/ipynb_output_filter.py
jupyter_notes/__init__.py
create_jupyter_git-0.0.2.dist-info/METADATA
create_jupyter_git-0.0.2.dist-info/WHEEL
create_jupyter_git-0.0.2.dist-info/entry_points.txt
create_jupyter_git-0.0.2.dist-info/top_level.txt
create_jupyter_git-0.0.2.dist-info/RECORD
