Metadata-Version: 2.1
Name: create-jupyter-git
Version: 0.0.2
Summary: A CLI command that generates a fresh Git Repository with files and configs to optimize version control for Jupyter Notebooks
Home-page: https://github.com/gitsome/create-jupyter-git
Author: John Martin
Author-email: johndavidfive@gmail.com
License: MIT
Platform: UNKNOWN
Classifier: License :: OSI Approved :: MIT License
Classifier: Programming Language :: Python :: 3
Classifier: Programming Language :: Python :: 3.5
Requires-Dist: click (==7.1.2)
Requires-Dist: Colr (==0.9.1)
Requires-Dist: pyfiglet (==0.8.post1)
